forwarg.py
forwarg-1.0.0.dist-info/DESCRIPTION.rst
forwarg-1.0.0.dist-info/METADATA
forwarg-1.0.0.dist-info/RECORD
forwarg-1.0.0.dist-info/WHEEL
forwarg-1.0.0.dist-info/metadata.json
forwarg-1.0.0.dist-info/top_level.txt
